[
    {"src": "../img/Me.png", "alt": "Me in the Peak District"},
    {"src": "../img/MC-Web-Background.png", "alt": "Website background"},
    {"src": "../img/El-Gato.png", "alt": "El Gato"},
    {"src": "../img/Oak-tree.png", "alt": "A pixel art oak tree"},
    {"src": "../img/Pine-tree.png", "alt": "A pixel art pine tree"},
    {"src": "../img/Poppy.png", "alt": "A pixel art poppy"},
    {"src": "../img/Paint-palette.png", "alt": "A pixel art paint palette"},
    {"src": "../img/Spanner.png", "alt": "A pixel art spanner"},
    {"src": "../img/treetree.png", "alt": "A pixel art treeTree"}
]